ddenv/__init__.py
ddenv/__main__.py
ddenv/managers/__init__.py
ddenv/managers/core.py
ddenv/managers/util.py
ddenv/managers/yarn/Dockerfile
ddenv/managers/yarn/__init__.py
ddenv/managers/yarn/entrypoint.sh
ddenv/managers/yarn/manager.py
ddenv-0.1.2.dist-info/entry_points.txt
ddenv-0.1.2.dist-info/LICENSE
ddenv-0.1.2.dist-info/WHEEL
ddenv-0.1.2.dist-info/METADATA
ddenv-0.1.2.dist-info/RECORD
